{"question": "Based on the context, what conclusion would be deemed most suitable?", "ext_fil_pred": "choice_2", "input_len": 1585}
{"question": "Taking into account the context provided, what conclusion would be most appropriate?", "ext_fil_pred": "choice_2", "input_len": 1417}
{"question": "Based on the context, what conclusion would be deemed most suitable?", "ext_fil_pred": "choice_2", "input_len": 1551}
{"question": "In light of the context provided, what conclusion can be considered the most appropriate?", "ext_fil_pred": "choice_1", "input_len": 1483}
{"question": "Taking into account the context provided, what conclusion would be most appropriate?", "ext_fil_pred": "choice_1", "input_len": 1432}
{"question": "Based on the context, what conclusion would be deemed most suitable?", "ext_fil_pred": "choice_4", "input_len": 1557}
{"question": "In light of the context provided, what conclusion can be considered the most appropriate?", "ext_fil_pred": "choice_1", "input_len": 1492}
{"question": "What would be the most appropriate conclusion based on the given context?", "ext_fil_pred": "choice_4", "input_len": 1292}
{"question": "What would be the most appropriate conclusion based on the given context?", "ext_fil_pred": "choice_4", "input_len": 1280}
{"question": "Taking into account the context provided, what conclusion would be most appropriate?", "ext_fil_pred": "choice_3", "input_len": 1419}
{"question": "In light of the context provided, what conclusion can be considered the most appropriate?", "ext_fil_pred": "choice_1", "input_len": 1437}
{"question": "Considering the provided context, what conclusion would be deemed most suitable?", "ext_fil_pred": "choice_3", "input_len": 1776}
{"question": "Based on the context, what conclusion would be deemed most suitable?", "ext_fil_pred": "choice_2", "input_len": 1560}
{"question": "What would be the most appropriate conclusion based on the given context?", "ext_fil_pred": "choice_3", "input_len": 1276}
{"question": "Taking into account the context provided, what conclusion would be most appropriate?", "ext_fil_pred": "choice_4", "input_len": 1432}
{"question": "What would be the most appropriate conclusion based on the given context?", "ext_fil_pred": "choice_1", "input_len": 1293}
{"question": "In light of the context provided, what conclusion can be considered the most appropriate?", "ext_fil_pred": "choice_1", "input_len": 1531}
{"question": "Taking into account the context provided, what conclusion would be most appropriate?", "ext_fil_pred": "choice_4", "input_len": 1396}
{"question": "In light of the context provided, what conclusion can be considered the most appropriate?", "ext_fil_pred": "choice_1", "input_len": 1504}
{"question": "Considering the provided context, what conclusion would be deemed most suitable?", "ext_fil_pred": "choice_3", "input_len": 1805}
{"question": "Taking into account the context provided, what conclusion would be most appropriate?", "ext_fil_pred": "choice_4", "input_len": 1467}
{"question": "What would be the most appropriate conclusion based on the given context?", "ext_fil_pred": "choice_3", "input_len": 1298}
{"question": "In light of the context provided, what conclusion can be considered the most appropriate?", "ext_fil_pred": "choice_1", "input_len": 1489}
{"question": "In light of the context provided, what conclusion can be considered the most appropriate?", "ext_fil_pred": "choice_3", "input_len": 1506}
{"question": "What would be the most appropriate conclusion based on the given context?", "ext_fil_pred": "choice_3", "input_len": 1299}
{"question": "Taking into account the context provided, what conclusion would be most appropriate?", "ext_fil_pred": "choice_3", "input_len": 1422}
{"question": "What would be the most appropriate conclusion based on the given context?", "ext_fil_pred": "choice_1", "input_len": 1313}
{"question": "Taking into account the context provided, what conclusion would be most appropriate?", "ext_fil_pred": "choice_1", "input_len": 1408}
{"question": "Based on the context, what conclusion would be deemed most suitable?", "ext_fil_pred": "choice_2", "input_len": 1605}
{"question": "Based on the context, what conclusion would be deemed most suitable?", "ext_fil_pred": "choice_4", "input_len": 1590}
{"question": "What would be the most appropriate conclusion based on the given context?", "ext_fil_pred": "choice_2", "input_len": 1290}
{"question": "In light of the context provided, what conclusion can be considered the most appropriate?", "ext_fil_pred": "choice_2", "input_len": 1524}
{"question": "In light of the context provided, what conclusion can be considered the most appropriate?", "ext_fil_pred": "choice_3", "input_len": 1491}
{"question": "Based on the context, what conclusion would be deemed most suitable?", "ext_fil_pred": "choice_4", "input_len": 1578}
{"question": "Considering the provided context, what conclusion would be deemed most suitable?", "ext_fil_pred": "choice_1", "input_len": 1726}
{"question": "Taking into account the context provided, what conclusion would be most appropriate?", "ext_fil_pred": "choice_3", "input_len": 1402}
{"question": "Considering the provided context, what conclusion would be deemed most suitable?", "ext_fil_pred": "choice_2", "input_len": 1747}
{"question": "Based on the context, what conclusion would be deemed most suitable?", "ext_fil_pred": "choice_2", "input_len": 1556}
{"question": "Taking into account the context provided, what conclusion would be most appropriate?", "ext_fil_pred": "choice_4", "input_len": 1444}
{"question": "In light of the context provided, what conclusion can be considered the most appropriate?", "ext_fil_pred": "choice_1", "input_len": 1446}
{"question": "In light of the context provided, what conclusion can be considered the most appropriate?", "ext_fil_pred": "choice_1", "input_len": 1496}
{"question": "What would be the most appropriate conclusion based on the given context?", "ext_fil_pred": "choice_4", "input_len": 1302}
{"question": "Taking into account the context provided, what conclusion would be most appropriate?", "ext_fil_pred": "choice_1", "input_len": 1434}
{"question": "In light of the context provided, what conclusion can be considered the most appropriate?", "ext_fil_pred": "choice_4", "input_len": 1486}
{"question": "What would be the most appropriate conclusion based on the given context?", "ext_fil_pred": "choice_2", "input_len": 1293}
{"question": "Considering the provided context, what conclusion would be deemed most suitable?", "ext_fil_pred": "choice_1", "input_len": 1758}
{"question": "In light of the context provided, what conclusion can be considered the most appropriate?", "ext_fil_pred": "choice_1", "input_len": 1490}
{"question": "Considering the provided context, what conclusion would be deemed most suitable?", "ext_fil_pred": "choice_3", "input_len": 1790}
{"question": "Considering the provided context, what conclusion would be deemed most suitable?", "ext_fil_pred": "choice_2", "input_len": 1758}
{"question": "What would be the most appropriate conclusion based on the given context?", "ext_fil_pred": "choice_3", "input_len": 1332}
{"question": "What would be the most appropriate conclusion based on the given context?", "ext_fil_pred": "choice_4", "input_len": 1264}
{"question": "Considering the provided context, what conclusion would be deemed most suitable?", "ext_fil_pred": "choice_3", "input_len": 1772}
{"question": "In light of the context provided, what conclusion can be considered the most appropriate?", "ext_fil_pred": "choice_1", "input_len": 1516}
{"question": "Based on the context, what conclusion would be deemed most suitable?", "ext_fil_pred": "choice_1", "input_len": 1613}
{"question": "What would be the most appropriate conclusion based on the given context?", "ext_fil_pred": "choice_1", "input_len": 1306}
{"question": "Considering the provided context, what conclusion would be deemed most suitable?", "ext_fil_pred": "choice_3", "input_len": 1783}
{"question": "In light of the context provided, what conclusion can be considered the most appropriate?", "ext_fil_pred": "choice_1", "input_len": 1482}
{"question": "Taking into account the context provided, what conclusion would be most appropriate?", "ext_fil_pred": "choice_1", "input_len": 1468}
{"question": "Considering the provided context, what conclusion would be deemed most suitable?", "ext_fil_pred": "choice_2", "input_len": 1730}
{"question": "Taking into account the context provided, what conclusion would be most appropriate?", "ext_fil_pred": "choice_2", "input_len": 1393}
{"question": "Based on the context, what conclusion would be deemed most suitable?", "ext_fil_pred": "choice_1", "input_len": 1525}
{"question": "Based on the context, what conclusion would be deemed most suitable?", "ext_fil_pred": "choice_1", "input_len": 1501}
{"question": "Taking into account the context provided, what conclusion would be most appropriate?", "ext_fil_pred": "choice_1", "input_len": 1374}
{"question": "Taking into account the context provided, what conclusion would be most appropriate?", "ext_fil_pred": "choice_2", "input_len": 1357}
{"question": "Considering the provided context, what conclusion would be deemed most suitable?", "ext_fil_pred": "choice_2", "input_len": 1718}
{"question": "In light of the context provided, what conclusion can be considered the most appropriate?", "ext_fil_pred": "choice_1", "input_len": 1443}
{"question": "Considering the provided context, what conclusion would be deemed most suitable?", "ext_fil_pred": "choice_3", "input_len": 1720}
{"question": "Based on the context, what conclusion would be deemed most suitable?", "ext_fil_pred": "choice_1", "input_len": 1535}
{"question": "Taking into account the context provided, what conclusion would be most appropriate?", "ext_fil_pred": "choice_3", "input_len": 1394}
{"question": "Taking into account the context provided, what conclusion would be most appropriate?", "ext_fil_pred": "choice_2", "input_len": 1429}
{"question": "What would be the most appropriate conclusion based on the given context?", "ext_fil_pred": "choice_4", "input_len": 1244}
{"question": "Taking into account the context provided, what conclusion would be most appropriate?", "ext_fil_pred": "choice_4", "input_len": 1373}
{"question": "Based on the context, what conclusion would be deemed most suitable?", "ext_fil_pred": "choice_1", "input_len": 1500}
{"question": "Taking into account the context provided, what conclusion would be most appropriate?", "ext_fil_pred": "choice_4", "input_len": 1411}
{"question": "In light of the context provided, what conclusion can be considered the most appropriate?", "ext_fil_pred": "choice_1", "input_len": 1407}
{"question": "Considering the provided context, what conclusion would be deemed most suitable?", "ext_fil_pred": "choice_3", "input_len": 1740}
{"question": "In light of the context provided, what conclusion can be considered the most appropriate?", "ext_fil_pred": "choice_1", "input_len": 1421}
{"question": "In light of the context provided, what conclusion can be considered the most appropriate?", "ext_fil_pred": "choice_1", "input_len": 1440}
{"question": "What would be the most appropriate conclusion based on the given context?", "ext_fil_pred": "choice_4", "input_len": 1252}
{"question": "In light of the context provided, what conclusion can be considered the most appropriate?", "ext_fil_pred": "choice_1", "input_len": 1427}
{"question": "In light of the context provided, what conclusion can be considered the most appropriate?", "ext_fil_pred": "choice_1", "input_len": 1435}
{"question": "Based on the context, what conclusion would be deemed most suitable?", "ext_fil_pred": "choice_3", "input_len": 1568}
{"question": "In light of the context provided, what conclusion can be considered the most appropriate?", "ext_fil_pred": "choice_3", "input_len": 1454}
{"question": "In light of the context provided, what conclusion can be considered the most appropriate?", "ext_fil_pred": "choice_1", "input_len": 1380}
{"question": "Considering the provided context, what conclusion would be deemed most suitable?", "ext_fil_pred": "choice_1", "input_len": 1664}
{"question": "What would be the most appropriate conclusion based on the given context?", "ext_fil_pred": "choice_2", "input_len": 1241}
{"question": "Taking into account the context provided, what conclusion would be most appropriate?", "ext_fil_pred": "choice_4", "input_len": 1434}
{"question": "Taking into account the context provided, what conclusion would be most appropriate?", "ext_fil_pred": "choice_1", "input_len": 1485}
{"question": "In light of the context provided, what conclusion can be considered the most appropriate?", "ext_fil_pred": "choice_1", "input_len": 1459}
{"question": "Based on the context, what conclusion would be deemed most suitable?", "ext_fil_pred": "choice_3", "input_len": 1570}
{"question": "Based on the context, what conclusion would be deemed most suitable?", "ext_fil_pred": "choice_1", "input_len": 1500}
{"question": "In light of the context provided, what conclusion can be considered the most appropriate?", "ext_fil_pred": "choice_1", "input_len": 1400}
{"question": "In light of the context provided, what conclusion can be considered the most appropriate?", "ext_fil_pred": "choice_2", "input_len": 1472}
{"question": "Taking into account the context provided, what conclusion would be most appropriate?", "ext_fil_pred": "choice_1", "input_len": 1438}
{"question": "Considering the provided context, what conclusion would be deemed most suitable?", "ext_fil_pred": "choice_3", "input_len": 1743}
{"question": "Based on the context, what conclusion would be deemed most suitable?", "ext_fil_pred": "choice_1", "input_len": 1547}
{"question": "In light of the context provided, what conclusion can be considered the most appropriate?", "ext_fil_pred": "choice_1", "input_len": 1513}
{"question": "In light of the context provided, what conclusion can be considered the most appropriate?", "ext_fil_pred": "choice_3", "input_len": 1424}
{"question": "Considering the provided context, what conclusion would be deemed most suitable?", "ext_fil_pred": "choice_2", "input_len": 1716}
{"question": "Taking into account the context provided, what conclusion would be most appropriate?", "ext_fil_pred": "choice_3", "input_len": 1369}
{"question": "Taking into account the context provided, what conclusion would be most appropriate?", "ext_fil_pred": "choice_1", "input_len": 1354}
{"question": "Based on the context, what conclusion would be deemed most suitable?", "ext_fil_pred": "choice_2", "input_len": 1499}
{"question": "In light of the context provided, what conclusion can be considered the most appropriate?", "ext_fil_pred": "choice_4", "input_len": 1416}
{"question": "Taking into account the context provided, what conclusion would be most appropriate?", "ext_fil_pred": "choice_2", "input_len": 1350}
{"question": "Taking into account the context provided, what conclusion would be most appropriate?", "ext_fil_pred": "choice_1", "input_len": 1344}
{"question": "What would be the most appropriate conclusion based on the given context?", "ext_fil_pred": "choice_2", "input_len": 1223}
{"question": "In light of the context provided, what conclusion can be considered the most appropriate?", "ext_fil_pred": "choice_3", "input_len": 1399}
{"question": "Taking into account the context provided, what conclusion would be most appropriate?", "ext_fil_pred": "choice_1", "input_len": 1385}
{"question": "Considering the provided context, what conclusion would be deemed most suitable?", "ext_fil_pred": "choice_1", "input_len": 1674}
{"question": "In light of the context provided, what conclusion can be considered the most appropriate?", "ext_fil_pred": "choice_1", "input_len": 1406}
{"question": "What would be the most appropriate conclusion based on the given context?", "ext_fil_pred": "choice_2", "input_len": 1238}
{"question": "What would be the most appropriate conclusion based on the given context?", "ext_fil_pred": "choice_1", "input_len": 1224}
{"question": "Considering the provided context, what conclusion would be deemed most suitable?", "ext_fil_pred": "choice_1", "input_len": 1677}
{"question": "In light of the context provided, what conclusion can be considered the most appropriate?", "ext_fil_pred": "choice_1", "input_len": 1389}
{"question": "What would be the most appropriate conclusion based on the given context?", "ext_fil_pred": "choice_1", "input_len": 1210}
{"question": "Taking into account the context provided, what conclusion would be most appropriate?", "ext_fil_pred": "choice_2", "input_len": 1340}
{"question": "What would be the most appropriate conclusion based on the given context?", "ext_fil_pred": "choice_1", "input_len": 1210}
{"question": "Taking into account the context provided, what conclusion would be most appropriate?", "ext_fil_pred": "choice_1", "input_len": 1368}
{"question": "Taking into account the context provided, what conclusion would be most appropriate?", "ext_fil_pred": "choice_4", "input_len": 1350}
{"question": "What would be the most appropriate conclusion based on the given context?", "ext_fil_pred": "choice_3", "input_len": 1206}
{"question": "Considering the provided context, what conclusion would be deemed most suitable?", "ext_fil_pred": "choice_4", "input_len": 1663}
{"question": "Considering the provided context, what conclusion would be deemed most suitable?", "ext_fil_pred": "choice_2", "input_len": 1685}
{"question": "Based on the context, what conclusion would be deemed most suitable?", "ext_fil_pred": "choice_4", "input_len": 1467}
{"question": "Based on the context, what conclusion would be deemed most suitable?", "ext_fil_pred": "choice_3", "input_len": 1488}
{"question": "Considering the provided context, what conclusion would be deemed most suitable?", "ext_fil_pred": "choice_3", "input_len": 1670}
{"question": "Based on the context, what conclusion would be deemed most suitable?", "ext_fil_pred": "choice_1", "input_len": 1486}
{"question": "Taking into account the context provided, what conclusion would be most appropriate?", "ext_fil_pred": "choice_3", "input_len": 1335}
{"question": "Considering the provided context, what conclusion would be deemed most suitable?", "ext_fil_pred": "choice_1", "input_len": 1676}
{"question": "In light of the context provided, what conclusion can be considered the most appropriate?", "ext_fil_pred": "choice_3", "input_len": 1387}
{"question": "Based on the context, what conclusion would be deemed most suitable?", "ext_fil_pred": "choice_4", "input_len": 1497}
{"question": "Based on the context, what conclusion would be deemed most suitable?", "ext_fil_pred": "choice_2", "input_len": 1484}
{"question": "In light of the context provided, what conclusion can be considered the most appropriate?", "ext_fil_pred": "choice_4", "input_len": 1410}
{"question": "In light of the context provided, what conclusion can be considered the most appropriate?", "ext_fil_pred": "choice_3", "input_len": 1392}
{"question": "Taking into account the context provided, what conclusion would be most appropriate?", "ext_fil_pred": "choice_2", "input_len": 1353}
{"question": "Taking into account the context provided, what conclusion would be most appropriate?", "ext_fil_pred": "choice_4", "input_len": 1342}
{"question": "Taking into account the context provided, what conclusion would be most appropriate?", "ext_fil_pred": "choice_1", "input_len": 1331}
{"question": "In light of the context provided, what conclusion can be considered the most appropriate?", "ext_fil_pred": "choice_1", "input_len": 1392}
{"question": "Considering the provided context, what conclusion would be deemed most suitable?", "ext_fil_pred": "choice_4", "input_len": 1669}
{"question": "What would be the most appropriate conclusion based on the given context?", "ext_fil_pred": "choice_1", "input_len": 1212}
{"question": "In light of the context provided, what conclusion can be considered the most appropriate?", "ext_fil_pred": "choice_4", "input_len": 1395}
{"question": "Taking into account the context provided, what conclusion would be most appropriate?", "ext_fil_pred": "choice_3", "input_len": 1349}
{"question": "What would be the most appropriate conclusion based on the given context?", "ext_fil_pred": "choice_3", "input_len": 1220}
{"question": "What would be the most appropriate conclusion based on the given context?", "ext_fil_pred": "choice_1", "input_len": 1224}
{"question": "Considering the provided context, what conclusion would be deemed most suitable?", "ext_fil_pred": "choice_4", "input_len": 1685}
{"question": "Based on the context, what conclusion would be deemed most suitable?", "ext_fil_pred": "choice_1", "input_len": 1551}
{"question": "Taking into account the context provided, what conclusion would be most appropriate?", "ext_fil_pred": "choice_2", "input_len": 1386}
{"question": "Taking into account the context provided, what conclusion would be most appropriate?", "ext_fil_pred": "choice_1", "input_len": 1363}
{"question": "Considering the provided context, what conclusion would be deemed most suitable?", "ext_fil_pred": "choice_1", "input_len": 1680}
{"question": "In light of the context provided, what conclusion can be considered the most appropriate?", "ext_fil_pred": "choice_3", "input_len": 1402}
{"question": "What would be the most appropriate conclusion based on the given context?", "ext_fil_pred": "choice_2", "input_len": 1207}
{"question": "In light of the context provided, what conclusion can be considered the most appropriate?", "ext_fil_pred": "choice_1", "input_len": 1397}
{"question": "Based on the context, what conclusion would be deemed most suitable?", "ext_fil_pred": "choice_1", "input_len": 1501}
{"question": "Taking into account the context provided, what conclusion would be most appropriate?", "ext_fil_pred": "choice_2", "input_len": 1345}
{"question": "What would be the most appropriate conclusion based on the given context?", "ext_fil_pred": "choice_1", "input_len": 1211}
{"question": "What would be the most appropriate conclusion based on the given context?", "ext_fil_pred": "choice_4", "input_len": 1211}
{"question": "Considering the provided context, what conclusion would be deemed most suitable?", "ext_fil_pred": "choice_4", "input_len": 1678}
{"question": "What would be the most appropriate conclusion based on the given context?", "ext_fil_pred": "choice_2", "input_len": 1205}
{"question": "In light of the context provided, what conclusion can be considered the most appropriate?", "ext_fil_pred": "choice_1", "input_len": 1418}
{"question": "Based on the context, what conclusion would be deemed most suitable?", "ext_fil_pred": "choice_1", "input_len": 1500}
{"question": "Based on the context, what conclusion would be deemed most suitable?", "ext_fil_pred": "choice_2", "input_len": 1490}
{"question": "Based on the context, what conclusion would be deemed most suitable?", "ext_fil_pred": "choice_4", "input_len": 1513}
{"question": "Based on the context, what conclusion would be deemed most suitable?", "ext_fil_pred": "choice_4", "input_len": 1506}
{"question": "Taking into account the context provided, what conclusion would be most appropriate?", "ext_fil_pred": "choice_3", "input_len": 1357}
{"question": "Taking into account the context provided, what conclusion would be most appropriate?", "ext_fil_pred": "choice_4", "input_len": 1346}
{"question": "Considering the provided context, what conclusion would be deemed most suitable?", "ext_fil_pred": "choice_4", "input_len": 1662}
{"question": "Taking into account the context provided, what conclusion would be most appropriate?", "ext_fil_pred": "choice_1", "input_len": 1328}
{"question": "What would be the most appropriate conclusion based on the given context?", "ext_fil_pred": "choice_1", "input_len": 1222}
{"question": "Taking into account the context provided, what conclusion would be most appropriate?", "ext_fil_pred": "choice_1", "input_len": 1349}
{"question": "What would be the most appropriate conclusion based on the given context?", "ext_fil_pred": "choice_2", "input_len": 1213}
{"question": "Considering the provided context, what conclusion would be deemed most suitable?", "ext_fil_pred": "choice_2", "input_len": 1685}
{"question": "Taking into account the context provided, what conclusion would be most appropriate?", "ext_fil_pred": "choice_1", "input_len": 1332}
{"question": "What would be the most appropriate conclusion based on the given context?", "ext_fil_pred": "choice_3", "input_len": 1217}
{"question": "In light of the context provided, what conclusion can be considered the most appropriate?", "ext_fil_pred": "choice_1", "input_len": 1449}
{"question": "Taking into account the context provided, what conclusion would be most appropriate?", "ext_fil_pred": "choice_3", "input_len": 1330}
{"question": "What would be the most appropriate conclusion based on the given context?", "ext_fil_pred": "choice_4", "input_len": 1223}
{"question": "Considering the provided context, what conclusion would be deemed most suitable?", "ext_fil_pred": "choice_3", "input_len": 1666}
{"question": "Considering the provided context, what conclusion would be deemed most suitable?", "ext_fil_pred": "choice_1", "input_len": 1678}
{"question": "Based on the context, what conclusion would be deemed most suitable?", "ext_fil_pred": "choice_2", "input_len": 1470}
{"question": "Based on the context, what conclusion would be deemed most suitable?", "ext_fil_pred": "choice_3", "input_len": 1507}
{"question": "Based on the context, what conclusion would be deemed most suitable?", "ext_fil_pred": "choice_4", "input_len": 1469}
{"question": "What would be the most appropriate conclusion based on the given context?", "ext_fil_pred": "choice_4", "input_len": 1193}
{"question": "What would be the most appropriate conclusion based on the given context?", "ext_fil_pred": "choice_3", "input_len": 1209}
{"question": "Taking into account the context provided, what conclusion would be most appropriate?", "ext_fil_pred": "choice_4", "input_len": 1366}
{"question": "Based on the context, what conclusion would be deemed most suitable?", "ext_fil_pred": "choice_4", "input_len": 1487}
{"question": "What would be the most appropriate conclusion based on the given context?", "ext_fil_pred": "choice_3", "input_len": 1205}
{"question": "In light of the context provided, what conclusion can be considered the most appropriate?", "ext_fil_pred": "choice_1", "input_len": 1435}
{"question": "Considering the provided context, what conclusion would be deemed most suitable?", "ext_fil_pred": "choice_3", "input_len": 1702}
{"question": "Taking into account the context provided, what conclusion would be most appropriate?", "ext_fil_pred": "choice_4", "input_len": 1368}
{"question": "What would be the most appropriate conclusion based on the given context?", "ext_fil_pred": "choice_1", "input_len": 1214}
{"question": "In light of the context provided, what conclusion can be considered the most appropriate?", "ext_fil_pred": "choice_1", "input_len": 1459}
{"question": "Taking into account the context provided, what conclusion would be most appropriate?", "ext_fil_pred": "choice_2", "input_len": 1400}
{"question": "In light of the context provided, what conclusion can be considered the most appropriate?", "ext_fil_pred": "choice_1", "input_len": 1421}
{"question": "What would be the most appropriate conclusion based on the given context?", "ext_fil_pred": "choice_1", "input_len": 1234}
{"question": "What would be the most appropriate conclusion based on the given context?", "ext_fil_pred": "choice_1", "input_len": 1319}
{"question": "What would be the most appropriate conclusion based on the given context?", "ext_fil_pred": "choice_4", "input_len": 1215}
{"question": "In light of the context provided, what conclusion can be considered the most appropriate?", "ext_fil_pred": "choice_3", "input_len": 1433}
{"question": "In light of the context provided, what conclusion can be considered the most appropriate?", "ext_fil_pred": "choice_1", "input_len": 1420}
{"question": "Considering the provided context, what conclusion would be deemed most suitable?", "ext_fil_pred": "choice_2", "input_len": 1673}
{"question": "Taking into account the context provided, what conclusion would be most appropriate?", "ext_fil_pred": "choice_1", "input_len": 1372}
{"question": "Taking into account the context provided, what conclusion would be most appropriate?", "ext_fil_pred": "choice_1", "input_len": 1399}
